NetkillerLinux/README.md
NetkillerLinux/__init__.py
NetkillerLinux/__main__.py
NetkillerLinux/file.epub
NetkillerLinux/index.html
NetkillerLinux/css/__init__.py
NetkillerLinux/css/annotations.css
NetkillerLinux/css/main.css
NetkillerLinux/css/normalize.css
NetkillerLinux/css/popup.css
NetkillerLinux/font/__init__.py
NetkillerLinux/font/fontello.eot
NetkillerLinux/font/fontello.svg
NetkillerLinux/font/fontello.ttf
NetkillerLinux/font/fontello.woff
NetkillerLinux/img/__init__.py
NetkillerLinux/img/annotator-glyph-sprite.png
NetkillerLinux/img/annotator-icon-sprite.png
NetkillerLinux/img/apple-touch-icon.png
NetkillerLinux/img/cancelfullscreen.png
NetkillerLinux/img/close.png
NetkillerLinux/img/fullscreen.png
NetkillerLinux/img/loader.gif
NetkillerLinux/img/menu-icon.png
NetkillerLinux/img/save.png
NetkillerLinux/img/saved.png
NetkillerLinux/img/settings-s.png
NetkillerLinux/img/settings.png
NetkillerLinux/img/star.png
NetkillerLinux/js/__init__.py
NetkillerLinux/js/epub.js
NetkillerLinux/js/epub.min.js
NetkillerLinux/js/epub.min.map
NetkillerLinux/js/hooks.min.js
NetkillerLinux/js/hooks.min.map
NetkillerLinux/js/reader.js
NetkillerLinux/js/reader.js.map
NetkillerLinux/js/reader.min.js
NetkillerLinux/js/reader.min.map
NetkillerLinux/js/hooks/__init__.py
NetkillerLinux/js/hooks/extensions/__init__.py
NetkillerLinux/js/hooks/extensions/highlight.js
NetkillerLinux/js/libs/__init__.py
NetkillerLinux/js/libs/jquery.min.js
NetkillerLinux/js/libs/localforage.min.js
NetkillerLinux/js/libs/screenfull.js
NetkillerLinux/js/libs/screenfull.min.js
NetkillerLinux/js/libs/zip.min.js
NetkillerLinux/js/plugins/__init__.py
NetkillerLinux/js/plugins/hypothesis.js
NetkillerLinux/js/plugins/search.js
netkiller_linux-2024.3.5.0.dist-info/METADATA
netkiller_linux-2024.3.5.0.dist-info/WHEEL
netkiller_linux-2024.3.5.0.dist-info/entry_points.txt
netkiller_linux-2024.3.5.0.dist-info/top_level.txt
netkiller_linux-2024.3.5.0.dist-info/RECORD
